adafruit_mlx90640.py
adafruit_circuitpython_mlx90640-1.3.3.dist-info/LICENSE
adafruit_circuitpython_mlx90640-1.3.3.dist-info/METADATA
adafruit_circuitpython_mlx90640-1.3.3.dist-info/WHEEL
adafruit_circuitpython_mlx90640-1.3.3.dist-info/top_level.txt
adafruit_circuitpython_mlx90640-1.3.3.dist-info/RECORD
